devdeck_obs/__init__.py
devdeck_obs/obs_control.py
devdeck_obs-0.1.2.dist-info/WHEEL
devdeck_obs-0.1.2.dist-info/METADATA
devdeck_obs-0.1.2.dist-info/RECORD
