Metadata-Version: 2.1
Name: devdeck-obs
Version: 0.1.2
Summary: OBS support for DevDeck
Author: Tom Whitwell
Author-email: tom@whi.tw
Requires-Python: >=3.10,<4.0
Classifier: Programming Language :: Python :: 3
Classifier: Programming Language :: Python :: 3.10
